fix_includes/__init__.py
fix_includes/base.py
fix_includes/fix_includes.py
fix_includes/fix_includes_test.py
fix_includes/fix_js_requires.py
fix_includes/fix_python_imports.py
fix_includes/fix_python_imports_test.py
fix_includes-0.2.dist-info/DESCRIPTION.rst
fix_includes-0.2.dist-info/METADATA
fix_includes-0.2.dist-info/RECORD
fix_includes-0.2.dist-info/WHEEL
fix_includes-0.2.dist-info/entry_points.txt
fix_includes-0.2.dist-info/metadata.json
fix_includes-0.2.dist-info/top_level.txt
