Metadata-Version: 2.0
Name: fix-includes
Version: 0.2
Summary: Fix-includes manages include/import/require lines in C, C++, Python, and JavaScript (node.js).
Home-page: https://github.com/csilvers/fix-includes
Author: Craig Silverstein
Author-email: csilvers+fix_includes@gmail.com
License: UNKNOWN
Keywords: import,include,python,nodejs
Platform: UNKNOWN
Classifier: License :: OSI Approved :: University of Illinois/NCSA Open Source License
Classifier: Programming Language :: Python :: 2
Classifier: Programming Language :: Python :: 2.7
